mongomock_mate/__init__.py
mongomock_mate/__init__.pyc
mongomock_mate/patch_collection.py
mongomock_mate/patch_collection.pyc
mongomock_mate/patch_database.py
mongomock_mate/patch_database.pyc
mongomock_mate/patch_write_concern.py
mongomock_mate/patch_write_concern.pyc
mongomock_mate/sixmini.py
mongomock_mate/sixmini.pyc
mongomock_mate/__pycache__/__init__.cpython-34.pyc
mongomock_mate/__pycache__/__init__.cpython-35.pyc
mongomock_mate/__pycache__/__init__.cpython-36.pyc
mongomock_mate/__pycache__/patch_collection.cpython-34.pyc
mongomock_mate/__pycache__/patch_collection.cpython-35.pyc
mongomock_mate/__pycache__/patch_collection.cpython-36.pyc
mongomock_mate/__pycache__/patch_database.cpython-34.pyc
mongomock_mate/__pycache__/patch_database.cpython-35.pyc
mongomock_mate/__pycache__/patch_database.cpython-36.pyc
mongomock_mate/__pycache__/patch_write_concern.cpython-34.pyc
mongomock_mate/__pycache__/patch_write_concern.cpython-35.pyc
mongomock_mate/__pycache__/patch_write_concern.cpython-36.pyc
mongomock_mate/__pycache__/sixmini.cpython-34.pyc
mongomock_mate/__pycache__/sixmini.cpython-35.pyc
mongomock_mate/__pycache__/sixmini.cpython-36.pyc
mongomock_mate-0.0.1.dist-info/METADATA
mongomock_mate-0.0.1.dist-info/RECORD
mongomock_mate-0.0.1.dist-info/WHEEL
mongomock_mate-0.0.1.dist-info/top_level.txt
